ends/__init__.py
ends/stats.py
ends/utils.py
ends/version.py
burnt_ends-0.0.1.dist-info/LICENSE
burnt_ends-0.0.1.dist-info/METADATA
burnt_ends-0.0.1.dist-info/WHEEL
burnt_ends-0.0.1.dist-info/top_level.txt
burnt_ends-0.0.1.dist-info/RECORD
