Metadata-Version: 2.1
Name: burnt-ends
Version: 0.0.1
Summary: A Python package containing modular, well-tested, utility and statistical functions handy for scientific computing and analysis.
Home-page: http://github.com/cosanlab/neighbors
Maintainer: Cosan Lab, Eshin Jolly
Maintainer-email: luke.j.chang@dartmouth.edu, eshin.jolly@dartmouth.edu
License: MIT
Keywords: statistics,utilities,social science,machine-learning,neuroscience,psychology,programming
Classifier: Programming Language :: Python :: 3.7
Classifier: Programming Language :: Python :: 3.8
Classifier: Programming Language :: Python :: 3.9
Classifier: Operating System :: OS Independent
Classifier: Intended Audience :: Science/Research
Classifier: License :: OSI Approved :: MIT License
License-File: LICENSE
Requires-Dist: pandas (>=1.2.0)
Requires-Dist: numpy (>=1.21)
Requires-Dist: seaborn (>=0.12.0)
Requires-Dist: matplotlib (>=3.3)
Requires-Dist: patsy (>=0.5.1)
Requires-Dist: joblib (>=1.1)
Requires-Dist: scipy (>=1.9.0)
